django_sql_query_logger-1.0.0.dist-info/licenses/LICENSE
sql_query_middlewares/__init__.py
sql_query_middlewares/middlewares.py
django_sql_query_logger-1.0.0.dist-info/METADATA
django_sql_query_logger-1.0.0.dist-info/WHEEL
django_sql_query_logger-1.0.0.dist-info/top_level.txt
django_sql_query_logger-1.0.0.dist-info/RECORD
